LICENSE
README.md
setup.py
automatic_ml_pack.egg-info/PKG-INFO
automatic_ml_pack.egg-info/SOURCES.txt
automatic_ml_pack.egg-info/dependency_links.txt
automatic_ml_pack.egg-info/requires.txt
automatic_ml_pack.egg-info/top_level.txt
modules/__init__.py
modules/exception.py
modules/logger.py
modules/utils.py
modules/components/__init__.py
modules/components/data_ingestion.py
modules/components/data_transformation.py
modules/components/model_trainer.py
modules/pipeline/__init__.py
modules/pipeline/predict_pipeline.py
modules/pipeline/train_pipeline.py